Metadata-Version: 2.1
Name: grib2io-interp
Version: 1.2.2
Summary: Interpolation component for grib2io providing a Python interface to NCEPLIBS-ip
Author-email: Eric Engle <eric.engle@noaa.gov>
License: MIT
Project-URL: Documentation, https://noaa-mdl.github.io/grib2io-interp
Project-URL: Respository, https://github.com/NOAA-MDL/grib2io-interp
Keywords: weather,data-science,numpy,meteorology,weather-data,atmospheric-science,grib2,grib2-decoder,grib2-encoder,ncep
Classifier: Development Status :: 5 - Production/Stable
Classifier: Environment :: Console
Classifier: Programming Language :: Python :: 3
Classifier: Programming Language :: Python :: 3 :: Only
Classifier: Programming Language :: Python :: 3.8
Classifier: Programming Language :: Python :: 3.9
Classifier: Programming Language :: Python :: 3.10
Classifier: Programming Language :: Python :: 3.11
Classifier: Intended Audience :: Science/Research
Classifier: License :: OSI Approved
Classifier: Topic :: Scientific/Engineering :: Atmospheric Science
Classifier: Topic :: Software Development :: Libraries :: Python Modules
Classifier: Operating System :: POSIX
Classifier: Operating System :: MacOS
Requires-Python: >=3.8
License-File: LICENSE
Requires-Dist: numpy
